datonius/__init__.py
datonius/cli.py
datonius/datonius.py
datonius/ontology.py
datonius/util.py
datonius-2.3.3.dist-info/AUTHORS.rst
datonius-2.3.3.dist-info/METADATA
datonius-2.3.3.dist-info/WHEEL
datonius-2.3.3.dist-info/entry_points.txt
datonius-2.3.3.dist-info/top_level.txt
datonius-2.3.3.dist-info/RECORD
