Metadata-Version: 2.1
Name: datonius
Version: 2.3.3
Summary: Python model package for the CFSAN Datonius framework (we're probably not calling it that.)
Home-page: https://github.com/crashfrog/datonius
Author: Justin Payne
Author-email: justin.payne@fda.hhs.gov
Keywords: datonius
Classifier: Development Status :: 2 - Pre-Alpha
Classifier: Intended Audience :: Developers
Classifier: Natural Language :: English
Classifier: Programming Language :: Python :: 3
Classifier: Programming Language :: Python :: 3.7
Classifier: Programming Language :: Python :: 3.8
Requires-Python: >=3.7
License-File: AUTHORS.rst
Requires-Dist: peewee (~=3.14.4)
Requires-Dist: psycopg2-binary (~=2.9.3)
Requires-Dist: boto3 (~=1.17.53)
Requires-Dist: tabulate (~=0.8.9)
Requires-Dist: click
Requires-Dist: simplejson (~=3.17.2)
Requires-Dist: owlready2 (~=0.46)
Requires-Dist: requests (~=2.28.0)
Requires-Dist: rdflib (~=6.3.2)
